Workbook

Sheet salesdaily
A1: datum | B1: M01AB | C1: M01AE | D1: N02BA | E1: N02BE | F1: N05B | G1: N05C | H1: R03 | I1: R06 | J1: Year | K1: Month | L1: Hour | M1: Weekday Name
A2: 41671 | B2: 0 | C2: 3.67 | D2: 3.4 | E2: 32.4 | F2: 7 | G2: 0 | H2: 0 | I2: 2 | J2: 2014 | K2: 1 | L2: 248 | M2: Thursday
A3: 41699 | B3: 8 | C3: 4 | D3: 4.4 | E3: 50.6 | F3: 16 | G3: 0 | H3: 20 | I3: 4 | J3: 2014 | K3: 1 | L3: 276 | M3: Friday
A4: 41730 | B4: 2 | C4: 1 | D4: 6.5 | E4: 61.85 | F4: 10 | G4: 0 | H4: 9 | I4: 1 | J4: 2014 | K4: 1 | L4: 276 | M4: Saturday
A5: 41760 | B5: 4 | C5: 3 | D5: 7 | E5: 41.1 | F5: 8 | G5: 0 | H5: 3 | I5: 0 | J5: 2014 | K5: 1 | L5: 276 | M5: Sunday
A6: 41791 | B6: 5 | C6: 1 | D6: 4.5 | E6: 21.7 | F6: 16 | G6: 2 | H6: 6 | I6: 2 | J6: 2014 | K6: 1 | L6: 276 | M6: Monday
A7: 41821 | B7: 0 | C7: 0 | D7: 0 | E7: 0 | F7: 0 | G7: 0 | H7: 0 | I7: 0 | J7: 2014 | K7: 1 | L7: 276 | M7: Tuesday
A8: 41852 | B8: 5.33 | C8: 3 | D8: 10.5 | E8: 26.4 | F8: 19 | G8: 1 | H8: 10 | I8: 0 | J8: 2014 | K8: 1 | L8: 276 | M8: Wednesday
A9: 41883 | B9: 7 | C9: 1.68 | D9: 8 | E9: 25 | F9: 16 | G9: 0 | H9: 3 | I9: 2 | J9: 2014 | K9: 1 | L9: 276 | M9: Thursday
A10: 41913 | B10: 5 | C10: 2 | D10: 2 | E10: 53.3 | F10: 15 | G10: 2 | H10: 0 | I10: 2 | J10: 2014 | K10: 1 | L10: 276 | M10: Friday
A11: 41944 | B11: 5 | C11: 4.34 | D11: 10.4 | E11: 52.3 | F11: 14 | G11: 0 | H11: 1 | I11: 0.2 | J11: 2014 | K11: 1 | L11: 276 | M11: Saturday
A12: 41974 | B12: 2 | C12: 0.66 | D12: 2.5 | E12: 12 | F12: 8 | G12: 0 | H12: 1 | I12: 1 | J12: 2014 | K12: 1 | L12: 276 | M12: Sunday
A13: 1/13/2014 | B13: 7.34 | C13: 7.66 | D13: 6.2 | E13: 52 | F13: 9 | G13: 0 | H13: 7 | I13: 1 | J13: 2014 | K13: 1 | L13: 276 | M13: Monday
A14: 1/14/2014 | B14: 6 | C14: 1.33 | D14: 12.3 | E14: 33.7 | F14: 6 | G14: 1 | H14: 0 | I14: 2 | J14: 2014 | K14: 1 | L14: 276 | M14: Tuesday
A15: 1/15/2014 | B15: 4 | C15: 2.34 | D15: 5 | E15: 26.7 | F15: 12 | G15: 2 | H15: 3 | I15: 3 | J15: 2014 | K15: 1 | L15: 276 | M15: Wednesday
A16: 1/16/2014 | B16: 6 | C16: 2 | D16: 4.3 | E16: 28.3 | F16: 19 | G16: 1 | H16: 5 | I16: 0 | J16: 2014 | K16: 1 | L16: 276 | M16: Thursday
A17: 1/17/2014 | B17: 2 | C17: 3.68 | D17: 8.3 | E17: 20.4 | F17: 15 | G17: 0 | H17: 6 | I17: 3 | J17: 2014 | K17: 1 | L17: 276 | M17: Friday
A18: 1/18/2014 | B18: 1 | C18: 5.33 | D18: 5.8 | E18: 43.2 | F18: 15 | G18: 4 | H18: 7 | I18: 2 | J18: 2014 | K18: 1 | L18: 276 | M18: Saturday
A19: 1/19/2014 | B19: 4.33 | C19: 4 | D19: 4 | E19: 14.1 | F19: 4 | G19: 0 | H19: 1 | I19: 1 | J19: 2014 | K19: 1 | L19: 276 | M19: Sunday
A20: 1/20/2014 | B20: 6 | C20: 3.34 | D20: 3.3 | E20: 11.9 | F20: 18 | G20: 2 | H20: 12 | I20: 3 | J20: 2014 | K20: 1 | L20: 276 | M20: Monday
A21: 1/21/2014 | B21: 2 | C21: 3.34 | D21: 4 | E21: 42 | F21: 15 | G21: 2 | H21: 0 | I21: 1 | J21: 2014 | K21: 1 | L21: 276 | M21: Tuesday
A22: 1/22/2014 | B22: 7 | C22: 3 | D22: 7 | E22: 18.1 | F22: 10 | G22: 0 | H22: 5 | I22: 2 | J22: 2014 | K22: 1 | L22: 276 | M22: Wednesday
A23: 1/23/2014 | B23: 4 | C23: 4.67 | D23: 5.2 | E23: 26.2 | F23: 2 | G23: 3 | H23: 1 | I23: 3 | J23: 2014 | K23: 1 | L23: 276 | M23: Thursday
A24: 1/24/2014 | B24: 4.67 | C24: 7.34 | D24: 7 | E24: 19.6 | F24: 13 | G24: 1 | H24: 0 | I24: 0 | J24: 2014 | K24: 1 | L24: 276 | M24: Friday
... A31: 1/31/2014 | B31: 1 | C31: 2.68 | D31: 7.1 | E31: 26.9 | F31: 9 | G31: 0 | H31: 1 | I31: 0 | J31: 2014 | K31: 1 | L31: 276 | M31: Friday
A32: 41641 | B32: 4.33 | C32: 4.32 | D32: 5 | E32: 43 | F32: 13 | G32: 1 | H32: 14 | I32: 0 | J32: 2014 | K32: 2 | L32: 276 | M32: Saturday
A33: 41672 | B33: 7 | C33: 3 | D33: 0.2 | E33: 13.5 | F33: 6 | G33: 2 | H33: 8 | I33: 0 | J33: 2014 | K33: 2 | L33: 276 | M33: Sunday
A34: 41700 | B34: 5 | C34: 1 | D34: 8.5 | E34: 32.4 | F34: 16 | G34: 1 | H34: 1 | I34: 0 | J34: 2014 | K34: 2 | L34: 276 | M34: Monday
A35: 41731 | B35: 1.33 | C35: 3 | D35: 7 | E35: 30.6 | F35: 8 | G35: 1 | H35: 17 | I35: 2 | J35: 2014 | K35: 2 | L35: 276 | M35: Tuesday
A36: 41761 | B36: 3 | C36: 4.02 | D36: 6.2 | E36: 32.4 | F36: 15 | G36: 1 | H36: 1 | I36: 1 | J36: 2014 | K36: 2 | L36: 276 | M36: Wednesday
A37: 41792 | B37: 3.33 | C37: 6.68 | D37: 3.5 | E37: 41.4 | F37: 17 | G37: 2 | H37: 5 | I37: 2 | J37: 2014 | K37: 2 | L37: 276 | M37: Thursday
A38: 41822 | B38: 2.66 | C38: 8.67 | D38: 11.7 | E38: 21.4 | F38: 19 | G38: 1 | H38: 0 | I38: 0 | J38: 2014 | K38: 2 | L38: 276 | M38: Friday
A39: 41853 | B39: 3.33 | C39: 3.35 | D39: 14.4 | E39: 37.1 | F39: 13 | G39: 1 | H39: 1 | I39: 1 | J39: 2014 | K39: 2 | L39: 276 | M39: Saturday
A40: 41884 | B40: 4 | C40: 3 | D40: 2 | E40: 31.5 | F40: 10 | G40: 0 | H40: 6 | I40: 0 | J40: 2014 | K40: 2 | L40: 276 | M40: Sunday
A41: 41914 | B41: 5 | C41: 10.33 | D41: 8.5 | E41: 40.1 | F41: 20 | G41: 3 | H41: 3 | I41: 1 | J41: 2014 | K41: 2 | L41: 276 | M41: Monday
A42: 41945 | B42: 10 | C42: 6.99 | D42: 13.3 | E42: 44.6 | F42: 20 | G42: 2 | H42: 6 | I42: 2.2 | J42: 2014 | K42: 2 | L42: 276 | M42: Tuesday
A43: 41975 | B43: 9 | C43: 1.67 | D43: 9.1 | E43: 73.6 | F43: 9 | G43: 0 | H43: 5 | I43: 0 | J43: 2014 | K43: 2 | L43: 276 | M43: Wednesday
A44: 2/13/2014 | B44: 4.33 | C44: 3.67 | D44: 10 | E44: 49.1 | F44: 13 | G44: 3 | H44: 0 | I44: 1 | J44: 2014 | K44: 2 | L44: 276 | M44: Thursday
A45: 2/14/2014 | B45: 4 | C45: 4.01 | D45: 3.2 | E45: 42.3 | F45: 13 | G45: 4 | H45: 0 | I45: 6 | J45: 2014 | K45: 2 | L45: 276 | M45: Friday
A46: 2/15/2014 | B46: 1 | C46: 2.34 | D46: 2 | E46: 37 | F46: 9 | G46: 0 | H46: 1 | I46: 5 | J46: 2014 | K46: 2 | L46: 276 | M46: Saturday
A47: 2/16/2014 | B47: 0 | C47: 1.68 | D47: 1.2 | E47: 34 | F47: 5 | G47: 2 | H47: 3 | I47: 1 | J47: 2014 | K47: 2 | L47: 276 | M47: Sunday
A48: 2/17/2014 | B48: 7.34 | C48: 4 | D48: 12.7 | E48: 27 | F48: 13 | G48: 1 | H48: 7 | I48: 0 | J48: 2014 | K48: 2 | L48: 276 | M48: Monday
A49: 2/18/2014 | B49: 7.34 | C49: 7.36 | D49: 6.1 | E49: 45 | F49: 14 | G49: 0 | H49: 13 | I49: 5 | J49: 2014 | K49: 2 | L49: 276 | M49: Tuesday
A50: 2/19/2014 | B50: 3.33 | C50: 5.02 | D50: 5.5 | E50: 66.8 | F50: 17 | G50: 1 | H50: 6 | I50: 1 | J50: 2014 | K50: 2 | L50: 276 | M50: Wednesday
A51: 2/20/2014 | B51: 7 | C51: 7.02 | D51: 3.2 | E51: 21.5 | F51: 16 | G51: 3 | H51: 8 | I51: 1 | J51: 2014 | K51: 2 | L51: 276 | M51: Thursday
A52: 2/21/2014 | B52: 6 | C52: 4.34 | D52: 9 | E52: 25.4 | F52: 17 | G52: 0 | H52: 0 | I52: 0 | J52: 2014 | K52: 2 | L52: 276 | M52: Friday
A53: 2/22/2014 | B53: 7 | C53: 3.17 | D53: 5.7 | E53: 26 | F53: 12 | G53: 0 | H53: 1 | I53: 0 | J53: 2014 | K53: 2 | L53: 276 | M53: Saturday
A54: 2/23/2014 | B54: 1 | C54: 3.34 | D54: 2 | E54: 21 | F54: 10 | G54: 0 | H54: 0 | I54: 0 | J54: 2014 | K54: 2 | L54: 276 | M54: Sunday
A55: 2/24/2014 | B55: 7 | C55: 4.68 | D55: 5.5 | E55: 26.5 | F55: 4 | G55: 0 | H55: 0 | I55: 3 | J55: 2014 | K55: 2 | L55: 276 | M55: Monday
... A59: 2/28/2014 | B59: 7 | C59: 7.36 | D59: 5.3 | E59: 37 | F59: 12 | G59: 1 | H59: 2 | I59: 0 | J59: 2014 | K59: 2 | L59: 276 | M59: Friday
A60: 41642 | B60: 6.34 | C60: 3.68 | D60: 11.355 | E60: 50.7 | F60: 8 | G60: 0 | H60: 0 | I60: 2.1 | J60: 2014 | K60: 3 | L60: 276 | M60: Saturday
A61: 41673 | B61: 3.34 | C61: 1 | D61: 2 | E61: 6.6 | F61: 2 | G61: 0 | H61: 0 | I61: 1 | J61: 2014 | K61: 3 | L61: 276 | M61: Sunday
A62: 41701 | B62: 4 | C62: 3.68 | D62: 1.6 | E62: 22.1 | F62: 1 | G62: 2 | H62: 0 | I62: 2.2 | J62: 2014 | K62: 3 | L62: 276 | M62: Monday
A63: 41732 | B63: 5.34 | C63: 7.02 | D63: 7.2 | E63: 47.275 | F63: 9 | G63: 0 | H63: 5 | I63: 4 | J63: 2014 | K63: 3 | L63: 276 | M63: Tuesday
A64: 41762 | B64: 3.34 | C64: 1 | D64: 3 | E64: 25 | F64: 4 | G64: 0 | H64: 1 | I64: 0 | J64: 2014 | K64: 3 | L64: 276 | M64: Wednesday
A65: 41793 | B65: 3 | C65: 2 | D65: 5.5 | E65: 44.1 | F65: 17 | G65: 1 | H65: 5 | I65: 1 | J65: 2014 | K65: 3 | L65: 276 | M65: Thursday
A66: 41823 | B66: 4 | C66: 4.34 | D66: 9.5 | E66: 25 | F66: 3 | G66: 1 | H66: 0 | I66: 2 | J66: 2014 | K66: 3 | L66: 276 | M66: Friday
A67: 41854 | B67: 4.34 | C67: 3.07 | D67: 1 | E67: 27.6 | F67: 11 | G67: 0 | H67: 0 | I67: 0 | J67: 2014 | K67: 3 | L67: 276 | M67: Saturday
A68: 41885 | B68: 1 | C68: 0 | D68: 4 | E68: 11.3 | F68: 3 | G68: 0 | H68: 5 | I68: 0 | J68: 2014 | K68: 3 | L68: 276 | M68: Sunday
A69: 41915 | B69: 6.68 | C69: 5.35 | D69: 3.8 | E69: 47 | F69: 11 | G69: 0 | H69: 0 | I69: 2 | J69: 2014 | K69: 3 | L69: 276 | M69: Monday
A70: 41946 | B70: 6 | C70: 5.7 | D70: 7 | E70: 30.4 | F70: 12 | G70: 1 | H70: 1 | I70: 5 | J70: 2014 | K70: 3 | L70: 276 | M70: Tuesday
A71: 41976 | B71: 6.34 | C71: 2.68 | D71: 6.5 | E71: 19.6 | F71: 22 | G71: 3 | H71: 2 | I71: 2 | J71: 2014 | K71: 3 | L71: 276 | M71: Wednesday
A72: 3/13/2014 | B72: 2.31 | C72: 4.36 | D72: 5.3 | E72: 15.5 | F72: 10 | G72: 0 | H72: 26 | I72: 2 | J72: 2014 | K72: 3 | L72: 276 | M72: Thursday
A73: 3/14/2014 | B73: 4.34 | C73: 1.68 | D73: 1.2 | E73: 16 | F73: 11 | G73: 0 | H73: 1 | I73: 2 | J73: 2014 | K73: 3 | L73: 276 | M73: Friday
A74: 3/15/2014 | B74: 4 | C74: 2 | D74: 11 | E74: 23.3 | F74: 18 | G74: 1 | H74: 6 | I74: 2 | J74: 2014 | K74: 3 | L74: 276 | M74: Saturday
A75: 3/16/2014 | B75: 2.68 | C75: 2 | D75: 1.4 | E75: 13 | F75: 6 | G75: 0 | H75: 0 | I75: 4 | J75: 2014 | K75: 3 | L75: 276 | M75: Sunday
A76: 3/17/2014 | B76: 8.68 | C76: 3.34 | D76: 7 | E76: 37 | F76: 6 | G76: 1 | H76: 0 | I76: 1 | J76: 2014 | K76: 3 | L76: 276 | M76: Monday
A77: 3/18/2014 | B77: 8 | C77: 4 | D77: 5 | E77: 20.1 | F77: 9 | G77: 0 | H77: 0 | I77: 4 | J77: 2014 | K77: 3 | L77: 276 | M77: Tuesday
A78: 3/19/2014 | B78: 4 | C78: 3.02 | D78: 4 | E78: 21.8 | F78: 2 | G78: 0 | H78: 0 | I78: 2 | J78: 2014 | K78: 3 | L78: 276 | M78: Wednesday
A79: 3/20/2014 | B79: 3 | C79: 5.34 | D79: 1.6 | E79: 38.2 | F79: 5 | G79: 0 | H79: 7 | I79: 4.2 | J79: 2014 | K79: 3 | L79: 276 | M79: Thursday
A80: 3/21/2014 | B80: 6 | C80: 3.68 | D80: 4.5 | E80: 40 | F80: 4 | G80: 0 | H80: 2 | I80: 1 | J80: 2014 | K80: 3 | L80: 276 | M80: Friday
A81: 3/22/2014 | B81: 3.34 | C81: 2.34 | D81: 0 | E81: 26.3 | F81: 10 | G81: 2 | H81: 18 | I81: 8.4 | J81: 2014 | K81: 3 | L81: 276 | M81: Saturday
A82: 3/23/2014 | B82: 6.34 | C82: 2 | D82: 4 | E82: 19.4 | F82: 0 | G82: 1 | H82: 0 | I82: 3 | J82: 2014 | K82: 3 | L82: 276 | M82: Sunday
A83: 3/24/2014 | B83: 5.68 | C83: 1 | D83: 4 | E83: 23.6 | F83: 7 | G83: 0 | H83: 6 | I83: 3.5 | J83: 2014 | K83: 3 | L83: 276 | M83: Monday
... A90: 3/31/2014 | B90: 5.34 | C90: 2.34 | D90: 4 | E90: 15.4 | F90: 6 | G90: 1 | H90: 4 | I90: 6 | J90: 2014 | K90: 3 | L90: 276 | M90: Monday
A91: 41643 | B91: 4.34 | C91: 1.34 | D91: 6.5 | E91: 27.5 | F91: 5 | G91: 3 | H91: 3 | I91: 1 | J91: 2014 | K91: 4 | L91: 276 | M91: Tuesday
A92: 41674 | B92: 2 | C92: 4.68 | D92: 8.9 | E92: 23 | F92: 1 | G92: 0 | H92: 7 | I92: 3 | J92: 2014 | K92: 4 | L92: 276 | M92: Wednesday
A93: 41702 | B93: 1 | C93: 1.34 | D93: 3 | E93: 19.2 | F93: 4 | G93: 0 | H93: 0 | I93: 4 | J93: 2014 | K93: 4 | L93: 276 | M93: Thursday
A94: 41733 | B94: 3 | C94: 3.67 | D94: 3 | E94: 24 | F94: 9 | G94: 3 | H94: 8 | I94: 2 | J94: 2014 | K94: 4 | L94: 276 | M94: Friday
A95: 41763 | B95: 2 | C95: 7.68 | D95: 10 | E95: 25.6 | F95: 5 | G95: 0 | H95: 5 | I95: 3 | J95: 2014 | K95: 4 | L95: 276 | M95: Saturday
A96: 41794 | B96: 2 | C96: 1 | D96: 1 | E96: 19 | F96: 1 | G96: 0 | H96: 0 | I96: 1 | J96: 2014 | K96: 4 | L96: 276 | M96: Sunday
A97: 41824 | B97: 6.34 | C97: 6 | D97: 6.5 | E97: 31.5 | F97: 4 | G97: 0 | H97: 0 | I97: 1 | J97: 2014 | K97: 4 | L97: 276 | M97: Monday
A98: 41855 | B98: 4.34 | C98: 2.34 | D98: 1.7 | E98: 19 | F98: 6 | G98: 1 | H98: 0 | I98: 4.7 | J98: 2014 | K98: 4 | L98: 276 | M98: Tuesday
A99: 41886 | B99: 6 | C99: 1.02 | D99: 1 | E99: 18 | F99: 2 | G99: 1 | H99: 2 | I99: 2.6 | J99: 2014 | K99: 4 | L99: 276 | M99: Wednesday
A100: 41916 | B100: 3.33 | C100: 1.68 | D100: 1 | E100: 18 | F100: 10 | G100: 0 | H100: 4 | I100: 4 | J100: 2014 | K100: 4 | L100: 276 | M100: Thursday
A101: 41947 | B101: 6 | C101: 4 | D101: 3 | E101: 25 | F101: 2 | G101: 2 | H101: 0 | I101: 2 | J101: 2014 | K101: 4 | L101: 276 | M101: Friday
A102: 41977 | B102: 7.02 | C102: 3.34 | D102: 6 | E102: 23.5 | F102: 19 | G102: 0 | H102: 11 | I102: 4 | J102: 2014 | K102: 4 | L102: 276 | M102: Saturday
A103: 4/13/2014 | B103: 3 | C103: 2 | D103: 2 | E103: 6 | F103: 3 | G103: 0 | H103: 5 | I103: 2 | J103: 2014 | K103: 4 | L103: 276 | M103: Sunday
A104: 4/14/2014 | B104: 1.34 | C104: 4.68 | D104: 5.35 | E104: 28.28 | F104: 10 | G104: 0 | H104: 5 | I104: 5 | J104: 2014 | K104: 4 | L104: 276 | M104: Monday
A105: 4/15/2014 | B105: 4.34 | C105: 3 | D105: 6.4 | E105: 18.7 | F105: 12 | G105: 0 | H105: 10 | I105: 1 | J105: 2014 | K105: 4 | L105: 276 | M105: Tuesday
A106: 4/16/2014 | B106: 2 | C106: 1.01 | D106: 4.2 | E106: 25.62 | F106: 1 | G106: 0 | H106: 6 | I106: 4 | J106: 2014 | K106: 4 | L106: 276 | M106: Wednesday
A107: 4/17/2014 | B107: 5.34 | C107: 0.34 | D107: 7.2 | E107: 16 | F107: 19 | G107: 0 | H107: 0 | I107: 0 | J107: 2014 | K107: 4 | L107: 276 | M107: Thursday
A108: 4/18/2014 | B108: 7 | C108: 7 | D108: 8 | E108: 23.3 | F108: 10 | G108: 1 | H108: 0 | I108: 5 | J108: 2014 | K108: 4 | L108: 276 | M108: Friday
A109: 4/19/2014 | B109: 7.34 | C109: 3.35 | D109: 4 | E109: 22.3 | F109: 7 | G109: 0 | H109: 3 | I109: 5 | J109: 2014 | K109: 4 | L109: 276 | M109: Saturday
A110: 4/20/2014 | B110: 0 | C110: 0 | D110: 0 | E110: 0 | F110: 0 | G110: 0 | H110: 0 | I110: 0 | J110: 2014 | K110: 4 | L110: 276 | M110: Sunday
A111: 4/21/2014 | B111: 1.34 | C111: 1.68 | D111: 2.1 | E111: 13.5 | F111: 8 | G111: 0 | H111: 0 | I111: 1 | J111: 2014 | K111: 4 | L111: 276 | M111: Monday
A112: 4/22/2014 | B112: 5.34 | C112: 7.165 | D112: 3.3 | E112: 32 | F112: 8 | G112: 1 | H112: 0 | I112: 1 | J112: 2014 | K112: 4 | L112: 276 | M112: Tuesday
A113: 4/23/2014 | B113: 6.34 | C113: 2.34 | D113: 3 | E113: 24.9 | F113: 8 | G113: 1 | H113: 2 | I113: 1 | J113: 2014 | K113: 4 | L113: 276 | M113: Wednesday
A114: 4/24/2014 | B114: 2 | C114: 2 | D114: 1.1 | E114: 26 | F114: 6 | G114: 0 | H114: 6 | I114: 2 | J114: 2014 | K114: 4 | L114: 276 | M114: Thursday
... A120: 4/30/2014 | B120: 4.34 | C120: 2.68 | D120: 7 | E120: 43.1 | F120: 11 | G120: 0 | H120: 7 | I120: 4 | J120: 2014 | K120: 4 | L120: 276 | M120: Wednesday
...

Sheet fact_sales_daily_final
A1: date | B1: year | C1: month | D1: weekday | E1: drug_class | F1: units_sold
A2: 41671 | B2: 2014 | C2: 1 | D2: Thursday | E2: M01AB | F2: 0
A3: 41671 | B3: 2014 | C3: 1 | D3: Thursday | E3: M01AE | F3: 3.67
A4: 41671 | B4: 2014 | C4: 1 | D4: Thursday | E4: N02BA | F4: 3.4
A5: 41671 | B5: 2014 | C5: 1 | D5: Thursday | E5: N02BE | F5: 32.4
A6: 41671 | B6: 2014 | C6: 1 | D6: Thursday | E6: N05B | F6: 7
A7: 41671 | B7: 2014 | C7: 1 | D7: Thursday | E7: N05C | F7: 0
A8: 41671 | B8: 2014 | C8: 1 | D8: Thursday | E8: R03 | F8: 0
A9: 41671 | B9: 2014 | C9: 1 | D9: Thursday | E9: R06 | F9: 2
A10: 41699 | B10: 2014 | C10: 1 | D10: Friday | E10: M01AB | F10: 8
A11: 41699 | B11: 2014 | C11: 1 | D11: Friday | E11: M01AE | F11: 4
A12: 41699 | B12: 2014 | C12: 1 | D12: Friday | E12: N02BA | F12: 4.4
A13: 41699 | B13: 2014 | C13: 1 | D13: Friday | E13: N02BE | F13: 50.6
... A89: 41974 | B89: 2014 | C89: 1 | D89: Sunday | E89: R06 | F89: 1
A90: 1/13/2014 | B90: 2014 | C90: 1 | D90: Monday | E90: M01AB | F90: 7.34
A91: 1/13/2014 | B91: 2014 | C91: 1 | D91: Monday | E91: M01AE | F91: 7.66
A92: 1/13/2014 | B92: 2014 | C92: 1 | D92: Monday | E92: N02BA | F92: 6.2
A93: 1/13/2014 | B93: 2014 | C93: 1 | D93: Monday | E93: N02BE | F93: 52
A94: 1/13/2014 | B94: 2014 | C94: 1 | D94: Monday | E94: N05B | F94: 9
A95: 1/13/2014 | B95: 2014 | C95: 1 | D95: Monday | E95: N05C | F95: 0
A96: 1/13/2014 | B96: 2014 | C96: 1 | D96: Monday | E96: R03 | F96: 7
A97: 1/13/2014 | B97: 2014 | C97: 1 | D97: Monday | E97: R06 | F97: 1
A98: 1/14/2014 | B98: 2014 | C98: 1 | D98: Tuesday | E98: M01AB | F98: 6
A99: 1/14/2014 | B99: 2014 | C99: 1 | D99: Tuesday | E99: M01AE | F99: 1.33
A100: 1/14/2014 | B100: 2014 | C100: 1 | D100: Tuesday | E100: N02BA | F100: 12.3
A101: 1/14/2014 | B101: 2014 | C101: 1 | D101: Tuesday | E101: N02BE | F101: 33.7
... A241: 1/31/2014 | B241: 2014 | C241: 1 | D241: Friday | E241: R06 | F241: 0
A242: 41641 | B242: 2014 | C242: 2 | D242: Saturday | E242: M01AB | F242: 4.33
A243: 41641 | B243: 2014 | C243: 2 | D243: Saturday | E243: M01AE | F243: 4.32
A244: 41641 | B244: 2014 | C244: 2 | D244: Saturday | E244: N02BA | F244: 5
A245: 41641 | B245: 2014 | C245: 2 | D245: Saturday | E245: N02BE | F245: 43
A246: 41641 | B246: 2014 | C246: 2 | D246: Saturday | E246: N05B | F246: 13
A247: 41641 | B247: 2014 | C247: 2 | D247: Saturday | E247: N05C | F247: 1
A248: 41641 | B248: 2014 | C248: 2 | D248: Saturday | E248: R03 | F248: 14
A249: 41641 | B249: 2014 | C249: 2 | D249: Saturday | E249: R06 | F249: 0
A250: 41672 | B250: 2014 | C250: 2 | D250: Sunday | E250: M01AB | F250: 7
A251: 41672 | B251: 2014 | C251: 2 | D251: Sunday | E251: M01AE | F251: 3
A252: 41672 | B252: 2014 | C252: 2 | D252: Sunday | E252: N02BA | F252: 0.2
A253: 41672 | B253: 2014 | C253: 2 | D253: Sunday | E253: N02BE | F253: 13.5
... A337: 41975 | B337: 2014 | C337: 2 | D337: Wednesday | E337: R06 | F337: 0
A338: 2/13/2014 | B338: 2014 | C338: 2 | D338: Thursday | E338: M01AB | F338: 4.33
A339: 2/13/2014 | B339: 2014 | C339: 2 | D339: Thursday | E339: M01AE | F339: 3.67
A340: 2/13/2014 | B340: 2014 | C340: 2 | D340: Thursday | E340: N02BA | F340: 10
A341: 2/13/2014 | B341: 2014 | C341: 2 | D341: Thursday | E341: N02BE | F341: 49.1
A342: 2/13/2014 | B342: 2014 | C342: 2 | D342: Thursday | E342: N05B | F342: 13
A343: 2/13/2014 | B343: 2014 | C343: 2 | D343: Thursday | E343: N05C | F343: 3
A344: 2/13/2014 | B344: 2014 | C344: 2 | D344: Thursday | E344: R03 | F344: 0
A345: 2/13/2014 | B345: 2014 | C345: 2 | D345: Thursday | E345: R06 | F345: 1
A346: 2/14/2014 | B346: 2014 | C346: 2 | D346: Friday | E346: M01AB | F346: 4
A347: 2/14/2014 | B347: 2014 | C347: 2 | D347: Friday | E347: M01AE | F347: 4.01
A348: 2/14/2014 | B348: 2014 | C348: 2 | D348: Friday | E348: N02BA | F348: 3.2
A349: 2/14/2014 | B349: 2014 | C349: 2 | D349: Friday | E349: N02BE | F349: 42.3
... A465: 2/28/2014 | B465: 2014 | C465: 2 | D465: Friday | E465: R06 | F465: 0
A466: 41642 | B466: 2014 | C466: 3 | D466: Saturday | E466: M01AB | F466: 6.34
A467: 41642 | B467: 2014 | C467: 3 | D467: Saturday | E467: M01AE | F467: 3.68
A468: 41642 | B468: 2014 | C468: 3 | D468: Saturday | E468: N02BA | F468: 11.355
A469: 41642 | B469: 2014 | C469: 3 | D469: Saturday | E469: N02BE | F469: 50.7
A470: 41642 | B470: 2014 | C470: 3 | D470: Saturday | E470: N05B | F470: 8
A471: 41642 | B471: 2014 | C471: 3 | D471: Saturday | E471: N05C | F471: 0
A472: 41642 | B472: 2014 | C472: 3 | D472: Saturday | E472: R03 | F472: 0
A473: 41642 | B473: 2014 | C473: 3 | D473: Saturday | E473: R06 | F473: 2.1
A474: 41673 | B474: 2014 | C474: 3 | D474: Sunday | E474: M01AB | F474: 3.34
A475: 41673 | B475: 2014 | C475: 3 | D475: Sunday | E475: M01AE | F475: 1
A476: 41673 | B476: 2014 | C476: 3 | D476: Sunday | E476: N02BA | F476: 2
A477: 41673 | B477: 2014 | C477: 3 | D477: Sunday | E477: N02BE | F477: 6.6
... A561: 41976 | B561: 2014 | C561: 3 | D561: Wednesday | E561: R06 | F561: 2
A562: 3/13/2014 | B562: 2014 | C562: 3 | D562: Thursday | E562: M01AB | F562: 2.31
A563: 3/13/2014 | B563: 2014 | C563: 3 | D563: Thursday | E563: M01AE | F563: 4.36
A564: 3/13/2014 | B564: 2014 | C564: 3 | D564: Thursday | E564: N02BA | F564: 5.3
A565: 3/13/2014 | B565: 2014 | C565: 3 | D565: Thursday | E565: N02BE | F565: 15.5
A566: 3/13/2014 | B566: 2014 | C566: 3 | D566: Thursday | E566: N05B | F566: 10
A567: 3/13/2014 | B567: 2014 | C567: 3 | D567: Thursday | E567: N05C | F567: 0
A568: 3/13/2014 | B568: 2014 | C568: 3 | D568: Thursday | E568: R03 | F568: 26
A569: 3/13/2014 | B569: 2014 | C569: 3 | D569: Thursday | E569: R06 | F569: 2
A570: 3/14/2014 | B570: 2014 | C570: 3 | D570: Friday | E570: M01AB | F570: 4.34
A571: 3/14/2014 | B571: 2014 | C571: 3 | D571: Friday | E571: M01AE | F571: 1.68
A572: 3/14/2014 | B572: 2014 | C572: 3 | D572: Friday | E572: N02BA | F572: 1.2
A573: 3/14/2014 | B573: 2014 | C573: 3 | D573: Friday | E573: N02BE | F573: 16
... A713: 3/31/2014 | B713: 2014 | C713: 3 | D713: Monday | E713: R06 | F713: 6
A714: 41643 | B714: 2014 | C714: 4 | D714: Tuesday | E714: M01AB | F714: 4.34
A715: 41643 | B715: 2014 | C715: 4 | D715: Tuesday | E715: M01AE | F715: 1.34
A716: 41643 | B716: 2014 | C716: 4 | D716: Tuesday | E716: N02BA | F716: 6.5
A717: 41643 | B717: 2014 | C717: 4 | D717: Tuesday | E717: N02BE | F717: 27.5
A718: 41643 | B718: 2014 | C718: 4 | D718: Tuesday | E718: N05B | F718: 5
A719: 41643 | B719: 2014 | C719: 4 | D719: Tuesday | E719: N05C | F719: 3
A720: 41643 | B720: 2014 | C720: 4 | D720: Tuesday | E720: R03 | F720: 3
A721: 41643 | B721: 2014 | C721: 4 | D721: Tuesday | E721: R06 | F721: 1
A722: 41674 | B722: 2014 | C722: 4 | D722: Wednesday | E722: M01AB | F722: 2
A723: 41674 | B723: 2014 | C723: 4 | D723: Wednesday | E723: M01AE | F723: 4.68
A724: 41674 | B724: 2014 | C724: 4 | D724: Wednesday | E724: N02BA | F724: 8.9
A725: 41674 | B725: 2014 | C725: 4 | D725: Wednesday | E725: N02BE | F725: 23
... A809: 41977 | B809: 2014 | C809: 4 | D809: Saturday | E809: R06 | F809: 4
A810: 4/13/2014 | B810: 2014 | C810: 4 | D810: Sunday | E810: M01AB | F810: 3
A811: 4/13/2014 | B811: 2014 | C811: 4 | D811: Sunday | E811: M01AE | F811: 2
A812: 4/13/2014 | B812: 2014 | C812: 4 | D812: Sunday | E812: N02BA | F812: 2
A813: 4/13/2014 | B813: 2014 | C813: 4 | D813: Sunday | E813: N02BE | F813: 6
A814: 4/13/2014 | B814: 2014 | C814: 4 | D814: Sunday | E814: N05B | F814: 3
A815: 4/13/2014 | B815: 2014 | C815: 4 | D815: Sunday | E815: N05C | F815: 0
A816: 4/13/2014 | B816: 2014 | C816: 4 | D816: Sunday | E816: R03 | F816: 5
A817: 4/13/2014 | B817: 2014 | C817: 4 | D817: Sunday | E817: R06 | F817: 2
...

Sheet dim_drug_class
A1: drug_class | B1: therapy_area
A2: M01AB | B2: Anti-inflammatory & antirheumatic
A3: M01AE | B3: Anti-inflammatory & antirheumatic
A4: N02BA | B4: Analgesics
A5: N02BE | B5: Paracetamol-type analgesics
A6: N05B | B6: Anxiolytics
A7: N05C | B7: Hypnotics & sedatives
A8: R03 | B8: Airway disease drugs
A9: R06 | B9: Antihistamines

Sheet daily_demand_metrics
A1: drug_class | B1: avg_daily_units | C1: demand_std_dev | D1: volatility_index | E1: stability_score | F1: risk_category
A2: M01AB | B2: =AVERAGEIFS( fact_sales_daily_final!$F:$F, fact_sales_daily_final!$E:$E, A2 ) -> 5.0336833 | C2: {=_xlfn.STDEV.P( _xlfn._xlws.FILTER( fact_sales_daily_final!$F:$F, fact_sales_daily_final!$E:$E = A2 ) )} -> 2.7369285 | D2: =C2 / B2 -> 0.54372282 | E2: =MAX(0, 1 - D2) -> 0.45627718 | F2: =IF(D2>1,"High Risk", IF(D2>0.6,"Moderate Risk", "Low Risk")) -> Low Risk
A3: M01AE | B3: =AVERAGEIFS( fact_sales_daily_final!$F:$F, fact_sales_daily_final!$E:$E, A3 ) -> 3.8958303 | C3: {=_xlfn.STDEV.P( _xlfn._xlws.FILTER( fact_sales_daily_final!$F:$F, fact_sales_daily_final!$E:$E = A3 ) )} -> 2.13283 | D3: =C3 / B3 -> 0.54746482 | E3: =MAX(0, 1 - D3) -> 0.45253518 | F3: =IF(D3>1,"High Risk", IF(D3>0.6,"Moderate Risk", "Low Risk")) -> Low Risk
A4: N02BA | B4: =AVERAGEIFS( fact_sales_daily_final!$F:$F, fact_sales_daily_final!$E:$E, A4 ) -> 3.8804411 | C4: {=_xlfn.STDEV.P( _xlfn._xlws.FILTER( fact_sales_daily_final!$F:$F, fact_sales_daily_final!$E:$E = A4 ) )} -> 2.3834442 | D4: =C4 / B4 -> 0.6142199 | E4: =MAX(0, 1 - D4) -> 0.3857801 | F4: =IF(D4>1,"High Risk", IF(D4>0.6,"Moderate Risk", "Low Risk")) -> Moderate Risk
A5: N02BE | B5: =AVERAGEIFS( fact_sales_daily_final!$F:$F, fact_sales_daily_final!$E:$E, A5 ) -> 29.917095 | C5: {=_xlfn.STDEV.P( _xlfn._xlws.FILTER( fact_sales_daily_final!$F:$F, fact_sales_daily_final!$E:$E = A5 ) )} -> 15.587264 | D5: =C5 / B5 -> 0.52101527 | E5: =MAX(0, 1 - D5) -> 0.47898473 | F5: =IF(D5>1,"High Risk", IF(D5>0.6,"Moderate Risk", "Low Risk")) -> Low Risk
A6: N05B | B6: =AVERAGEIFS( fact_sales_daily_final!$F:$F, fact_sales_daily_final!$E:$E, A6 ) -> 8.8536265 | C6: {=_xlfn.STDEV.P( _xlfn._xlws.FILTER( fact_sales_daily_final!$F:$F, fact_sales_daily_final!$E:$E = A6 ) )} -> 5.6042737 | D6: =C6 / B6 -> 0.63299188 | E6: =MAX(0, 1 - D6) -> 0.36700812 | F6: =IF(D6>1,"High Risk", IF(D6>0.6,"Moderate Risk", "Low Risk")) -> Moderate Risk
A7: N05C | B7: =AVERAGEIFS( fact_sales_daily_final!$F:$F, fact_sales_daily_final!$E:$E, A7 ) -> 0.59352248 | C7: {=_xlfn.STDEV.P( _xlfn._xlws.FILTER( fact_sales_daily_final!$F:$F, fact_sales_daily_final!$E:$E = A7 ) )} -> 1.0927288 | D7: =C7 / B7 -> 1.8410908 | E7: =MAX(0, 1 - D7) -> 0 | F7: =IF(D7>1,"High Risk", IF(D7>0.6,"Moderate Risk", "Low Risk")) -> High Risk
A8: R03 | B8: =AVERAGEIFS( fact_sales_daily_final!$F:$F, fact_sales_daily_final!$E:$E, A8 ) -> 5.5122616 | C8: {=_xlfn.STDEV.P( _xlfn._xlws.FILTER( fact_sales_daily_final!$F:$F, fact_sales_daily_final!$E:$E = A8 ) )} -> 6.4272099 | D8: =C8 / B8 -> 1.1659842 | E8: =MAX(0, 1 - D8) -> 0 | F8: =IF(D8>1,"High Risk", IF(D8>0.6,"Moderate Risk", "Low Risk")) -> High Risk
A9: R06 | B9: =AVERAGEIFS( fact_sales_daily_final!$F:$F, fact_sales_daily_final!$E:$E, A9 ) -> 2.9001982 | C9: {=_xlfn.STDEV.P( _xlfn._xlws.FILTER( fact_sales_daily_final!$F:$F, fact_sales_daily_final!$E:$E = A9 ) )} -> 2.4152423 | D9: =C9 / B9 -> 0.83278524 | E9: =MAX(0, 1 - D9) -> 0.16721476 | F9: =IF(D9>1,"High Risk", IF(D9>0.6,"Moderate Risk", "Low Risk")) -> Moderate Risk

Sheet finance_assumptions
A1: drug_claas | B1: unit_price | D1: Cost Type | E1: % of Revenue
A2: M01AB | B2: 1 | D2: Manufacturing | E2: 0.55
A3: M01AE | B3: 1 | D3: Distribution | E3: 0.08
A4: N02BA | B4: 1 | D4: Marketing | E4: 0.12
A5: N02BE | B5: 1 | D5: Total Cost % | E5: 0.75
A6: N05B | B6: 1
A7: N05C | B7: 1
A8: R03 | B8: 1
A9: R06 | B9: 1

Sheet daily_financials
A1: date | B1: drug_class | C1: units_sold | D1: revenue | E1: total_cost | F1: profit | G1: profit_margin
A2: =fact_sales_daily_final!A2 -> 41671 | B2: =fact_sales_daily_final!E2 -> M01AB | C2: =fact_sales_daily_final!F2 -> 0 | D2: =C2 * VLOOKUP(B2, finance_assumptions!A:B, 2, FALSE) -> 0 | E2: =D2 * 0.75 -> 0 | F2: =D2 - E2 -> 0 | G2: =IF(D2=0, 0, F2/D2) -> 0
A3: =fact_sales_daily_final!A3 -> 41671 | B3: =fact_sales_daily_final!E3 -> M01AE | C3: =fact_sales_daily_final!F3 -> 3.67 | D3: =C3 * VLOOKUP(B3, finance_assumptions!A:B, 2, FALSE) -> 3.67 | E3: =D3 * 0.75 -> 2.7525 | F3: =D3 - E3 -> 0.9175 | G3: =IF(D3=0, 0, F3/D3) -> 0.25
A4: =fact_sales_daily_final!A4 -> 41671 | B4: =fact_sales_daily_final!E4 -> N02BA | C4: =fact_sales_daily_final!F4 -> 3.4 | D4: =C4 * VLOOKUP(B4, finance_assumptions!A:B, 2, FALSE) -> 3.4 | E4: =D4 * 0.75 -> 2.55 | F4: =D4 - E4 -> 0.85 | G4: =IF(D4=0, 0, F4/D4) -> 0.25
A5: =fact_sales_daily_final!A5 -> 41671 | B5: =fact_sales_daily_final!E5 -> N02BE | C5: =fact_sales_daily_final!F5 -> 32.4 | D5: =C5 * VLOOKUP(B5, finance_assumptions!A:B, 2, FALSE) -> 32.4 | E5: =D5 * 0.75 -> 24.3 | F5: =D5 - E5 -> 8.1 | G5: =IF(D5=0, 0, F5/D5) -> 0.25
A6: =fact_sales_daily_final!A6 -> 41671 | B6: =fact_sales_daily_final!E6 -> N05B | C6: =fact_sales_daily_final!F6 -> 7 | D6: =C6 * VLOOKUP(B6, finance_assumptions!A:B, 2, FALSE) -> 7 | E6: =D6 * 0.75 -> 5.25 | F6: =D6 - E6 -> 1.75 | G6: =IF(D6=0, 0, F6/D6) -> 0.25
A7: =fact_sales_daily_final!A7 -> 41671 | B7: =fact_sales_daily_final!E7 -> N05C | C7: =fact_sales_daily_final!F7 -> 0 | D7: =C7 * VLOOKUP(B7, finance_assumptions!A:B, 2, FALSE) -> 0 | E7: =D7 * 0.75 -> 0 | F7: =D7 - E7 -> 0 | G7: =IF(D7=0, 0, F7/D7) -> 0
A8: =fact_sales_daily_final!A8 -> 41671 | B8: =fact_sales_daily_final!E8 -> R03 | C8: =fact_sales_daily_final!F8 -> 0 | D8: =C8 * VLOOKUP(B8, finance_assumptions!A:B, 2, FALSE) -> 0 | E8: =D8 * 0.75 -> 0 | F8: =D8 - E8 -> 0 | G8: =IF(D8=0, 0, F8/D8) -> 0
A9: =fact_sales_daily_final!A9 -> 41671 | B9: =fact_sales_daily_final!E9 -> R06 | C9: =fact_sales_daily_final!F9 -> 2 | D9: =C9 * VLOOKUP(B9, finance_assumptions!A:B, 2, FALSE) -> 2 | E9: =D9 * 0.75 -> 1.5 | F9: =D9 - E9 -> 0.5 | G9: =IF(D9=0, 0, F9/D9) -> 0.25
A10: =fact_sales_daily_final!A10 -> 41699 | B10: =fact_sales_daily_final!E10 -> M01AB | C10: =fact_sales_daily_final!F10 -> 8 | D10: =C10 * VLOOKUP(B10, finance_assumptions!A:B, 2, FALSE) -> 8 | E10: =D10 * 0.75 -> 6 | F10: =D10 - E10 -> 2 | G10: =IF(D10=0, 0, F10/D10) -> 0.25
A11: =fact_sales_daily_final!A11 -> 41699 | B11: =fact_sales_daily_final!E11 -> M01AE | C11: =fact_sales_daily_final!F11 -> 4 | D11: =C11 * VLOOKUP(B11, finance_assumptions!A:B, 2, FALSE) -> 4 | E11: =D11 * 0.75 -> 3 | F11: =D11 - E11 -> 1 | G11: =IF(D11=0, 0, F11/D11) -> 0.25
A12: =fact_sales_daily_final!A12 -> 41699 | B12: =fact_sales_daily_final!E12 -> N02BA | C12: =fact_sales_daily_final!F12 -> 4.4 | D12: =C12 * VLOOKUP(B12, finance_assumptions!A:B, 2, FALSE) -> 4.4 | E12: =D12 * 0.75 -> 3.3 | F12: =D12 - E12 -> 1.1 | G12: =IF(D12=0, 0, F12/D12) -> 0.25
A13: =fact_sales_daily_final!A13 -> 41699 | B13: =fact_sales_daily_final!E13 -> N02BE | C13: =fact_sales_daily_final!F13 -> 50.6 | D13: =C13 * VLOOKUP(B13, finance_assumptions!A:B, 2, FALSE) -> 50.6 | E13: =D13 * 0.75 -> 37.95 | F13: =D13 - E13 -> 12.65 | G13: =IF(D13=0, 0, F13/D13) -> 0.25
... A16849: =fact_sales_daily_final!A16849 -> 43687 | B16849: =fact_sales_daily_final!E16849 -> R06 | C16849: =fact_sales_daily_final!F16849 -> 0 | D16849: =C16849 * VLOOKUP(B16849, finance_assumptions!A:B, 2, FALSE) -> 0 | E16849: =D16849 * 0.75 -> 0 | F16849: =D16849 - E16849 -> 0 | G16849: =IF(D16849=0, 0, F16849/D16849) -> 0

Sheet drug_financial_summary
A1: drug_class | B1: total_revenue | C1: total_profit | D1: avg_margin
A2: M01AB | B2: =SUMIFS(daily_financials!$D:$D, daily_financials!$B:$B, A2) -> 10600.937 | C2: =SUMIFS(daily_financials!$F:$F, daily_financials!$B:$B, A2) -> 2650.2343 | D2: =AVERAGEIFS(daily_financials!$G:$G, daily_financials!$B:$B, A2) -> 0.24525166
A3: M01AE | B3: =SUMIFS(daily_financials!$D:$D, daily_financials!$B:$B, A3) -> 8204.6186 | C3: =SUMIFS(daily_financials!$F:$F, daily_financials!$B:$B, A3) -> 2051.1547 | D3: =AVERAGEIFS(daily_financials!$G:$G, daily_financials!$B:$B, A3) -> 0.2457265
A4: N02BA | B4: =SUMIFS(daily_financials!$D:$D, daily_financials!$B:$B, A4) -> 8172.209 | C4: =SUMIFS(daily_financials!$F:$F, daily_financials!$B:$B, A4) -> 2043.0523 | D4: =AVERAGEIFS(daily_financials!$G:$G, daily_financials!$B:$B, A4) -> 0.24074074
A5: N02BE | B5: =SUMIFS(daily_financials!$D:$D, daily_financials!$B:$B, A5) -> 63005.403 | C5: =SUMIFS(daily_financials!$F:$F, daily_financials!$B:$B, A5) -> 15751.351 | D5: =AVERAGEIFS(daily_financials!$G:$G, daily_financials!$B:$B, A5) -> 0.24691358
A6: N05B | B6: =SUMIFS(daily_financials!$D:$D, daily_financials!$B:$B, A6) -> 18645.737 | C6: =SUMIFS(daily_financials!$F:$F, daily_financials!$B:$B, A6) -> 4661.4344 | D6: =AVERAGEIFS(daily_financials!$G:$G, daily_financials!$B:$B, A6) -> 0.24489554
A7: N05C | B7: =SUMIFS(daily_financials!$D:$D, daily_financials!$B:$B, A7) -> 1249.9583 | C7: =SUMIFS(daily_financials!$F:$F, daily_financials!$B:$B, A7) -> 312.48958 | D7: =AVERAGEIFS(daily_financials!$G:$G, daily_financials!$B:$B, A7) -> 0.080246914
A8: R03 | B8: =SUMIFS(daily_financials!$D:$D, daily_financials!$B:$B, A8) -> 11608.823 | C8: =SUMIFS(daily_financials!$F:$F, daily_financials!$B:$B, A8) -> 2902.2057 | D8: =AVERAGEIFS(daily_financials!$G:$G, daily_financials!$B:$B, A8) -> 0.19254511
A9: R06 | B9: =SUMIFS(daily_financials!$D:$D, daily_financials!$B:$B, A9) -> 6107.8175 | C9: =SUMIFS(daily_financials!$F:$F, daily_financials!$B:$B, A9) -> 1526.9544 | D9: =AVERAGEIFS(daily_financials!$G:$G, daily_financials!$B:$B, A9) -> 0.21961064

Sheet profit_at_risk
A1: drug_class | B1: base_profit | C1: profit_10pct_drop | D1: profit_20pct_drop | E1: loss_10pct | F1: loss_20pct | G1: risk_rank_20pct
A2: M01AB | B2: =drug_financial_summary!C2 -> 2650.2343 | C2: =B2 * 0.9 -> 2385.2108 | D2: =B2 * 0.8 -> 2120.1874 | E2: =B2 - C2 -> 265.02343 | F2: =B2 - D2 -> 530.04685 | G2: =RANK(F2, $F$2:$F$9, 0) -> 4
A3: M01AE | B3: =drug_financial_summary!C3 -> 2051.1547 | C3: =B3 * 0.9 -> 1846.0392 | D3: =B3 * 0.8 -> 1640.9237 | E3: =B3 - C3 -> 205.11547 | F3: =B3 - D3 -> 410.23093 | G3: =RANK(F3, $F$2:$F$9, 0) -> 5
A4: N02BA | B4: =drug_financial_summary!C4 -> 2043.0523 | C4: =B4 * 0.9 -> 1838.747 | D4: =B4 * 0.8 -> 1634.4418 | E4: =B4 - C4 -> 204.30523 | F4: =B4 - D4 -> 408.61045 | G4: =RANK(F4, $F$2:$F$9, 0) -> 6
A5: N02BE | B5: =drug_financial_summary!C5 -> 15751.351 | C5: =B5 * 0.9 -> 14176.216 | D5: =B5 * 0.8 -> 12601.081 | E5: =B5 - C5 -> 1575.1351 | F5: =B5 - D5 -> 3150.2701 | G5: =RANK(F5, $F$2:$F$9, 0) -> 1
A6: N05B | B6: =drug_financial_summary!C6 -> 4661.4344 | C6: =B6 * 0.9 -> 4195.2909 | D6: =B6 * 0.8 -> 3729.1475 | E6: =B6 - C6 -> 466.14344 | F6: =B6 - D6 -> 932.28687 | G6: =RANK(F6, $F$2:$F$9, 0) -> 2
A7: N05C | B7: =drug_financial_summary!C7 -> 312.48958 | C7: =B7 * 0.9 -> 281.24062 | D7: =B7 * 0.8 -> 249.99167 | E7: =B7 - C7 -> 31.248958 | F7: =B7 - D7 -> 62.497917 | G7: =RANK(F7, $F$2:$F$9, 0) -> 8
A8: R03 | B8: =drug_financial_summary!C8 -> 2902.2057 | C8: =B8 * 0.9 -> 2611.9852 | D8: =B8 * 0.8 -> 2321.7646 | E8: =B8 - C8 -> 290.22057 | F8: =B8 - D8 -> 580.44115 | G8: =RANK(F8, $F$2:$F$9, 0) -> 3
A9: R06 | B9: =drug_financial_summary!C9 -> 1526.9544 | C9: =B9 * 0.9 -> 1374.2589 | D9: =B9 * 0.8 -> 1221.5635 | E9: =B9 - C9 -> 152.69544 | F9: =B9 - D9 -> 305.39087 | G9: =RANK(F9, $F$2:$F$9, 0) -> 7

Sheet risk_vs_stability
A1: drug_class | B1: stability_score | C1: loss_20pct | D1: risk_bucket
A2: =profit_at_risk!A2 -> M01AB | B2: =daily_demand_metrics!E2 -> 0.45627718 | C2: =profit_at_risk!F2 -> 530.04685 | D2: =IF(AND(B2<0.3, C2>500), "High Risk / Low Stability", IF(AND(B2>=0.3, C2>500), "High Risk / Stable", IF(AND(B2<0.3, C2<=500), "Low Risk / Low Stability", "Low Risk / Stable"))) -> High Risk / Stable
A3: =profit_at_risk!A3 -> M01AE | B3: =daily_demand_metrics!E3 -> 0.45253518 | C3: =profit_at_risk!F3 -> 410.23093 | D3: =IF(AND(B3<0.3, C3>500), "High Risk / Low Stability", IF(AND(B3>=0.3, C3>500), "High Risk / Stable", IF(AND(B3<0.3, C3<=500), "Low Risk / Low Stability", "Low Risk / Stable"))) -> Low Risk / Stable
A4: =profit_at_risk!A4 -> N02BA | B4: =daily_demand_metrics!E4 -> 0.3857801 | C4: =profit_at_risk!F4 -> 408.61045 | D4: =IF(AND(B4<0.3, C4>500), "High Risk / Low Stability", IF(AND(B4>=0.3, C4>500), "High Risk / Stable", IF(AND(B4<0.3, C4<=500), "Low Risk / Low Stability", "Low Risk / Stable"))) -> Low Risk / Stable
A5: =profit_at_risk!A5 -> N02BE | B5: =daily_demand_metrics!E5 -> 0.47898473 | C5: =profit_at_risk!F5 -> 3150.2701 | D5: =IF(AND(B5<0.3, C5>500), "High Risk / Low Stability", IF(AND(B5>=0.3, C5>500), "High Risk / Stable", IF(AND(B5<0.3, C5<=500), "Low Risk / Low Stability", "Low Risk / Stable"))) -> High Risk / Stable
A6: =profit_at_risk!A6 -> N05B | B6: =daily_demand_metrics!E6 -> 0.36700812 | C6: =profit_at_risk!F6 -> 932.28687 | D6: =IF(AND(B6<0.3, C6>500), "High Risk / Low Stability", IF(AND(B6>=0.3, C6>500), "High Risk / Stable", IF(AND(B6<0.3, C6<=500), "Low Risk / Low Stability", "Low Risk / Stable"))) -> High Risk / Stable
A7: =profit_at_risk!A7 -> N05C | B7: =daily_demand_metrics!E7 -> 0 | C7: =profit_at_risk!F7 -> 62.497917 | D7: =IF(AND(B7<0.3, C7>500), "High Risk / Low Stability", IF(AND(B7>=0.3, C7>500), "High Risk / Stable", IF(AND(B7<0.3, C7<=500), "Low Risk / Low Stability", "Low Risk / Stable"))) -> Low Risk / Low Stability
A8: =profit_at_risk!A8 -> R03 | B8: =daily_demand_metrics!E8 -> 0 | C8: =profit_at_risk!F8 -> 580.44115 | D8: =IF(AND(B8<0.3, C8>500), "High Risk / Low Stability", IF(AND(B8>=0.3, C8>500), "High Risk / Stable", IF(AND(B8<0.3, C8<=500), "Low Risk / Low Stability", "Low Risk / Stable"))) -> High Risk / Low Stability
A9: =profit_at_risk!A9 -> R06 | B9: =daily_demand_metrics!E9 -> 0.16721476 | C9: =profit_at_risk!F9 -> 305.39087 | D9: =IF(AND(B9<0.3, C9>500), "High Risk / Low Stability", IF(AND(B9>=0.3, C9>500), "High Risk / Stable", IF(AND(B9<0.3, C9<=500), "Low Risk / Low Stability", "Low Risk / Stable"))) -> Low Risk / Low Stability
